pcd/__init__.py
pcd/prominent_colors_detector.py
image_pcd-1.3.0.dist-info/LICENSE
image_pcd-1.3.0.dist-info/METADATA
image_pcd-1.3.0.dist-info/WHEEL
image_pcd-1.3.0.dist-info/top_level.txt
image_pcd-1.3.0.dist-info/RECORD
