Metadata-Version: 2.1
Name: image-pcd
Version: 1.3.0
Summary: A engine which detects prominent colors from the image.
Home-page: https://github.com/divy9881/prominent-colors-detector
Author: Divy Patel
Author-email: divy9881@gmail.com
License: MIT
Platform: UNKNOWN
Classifier: License :: OSI Approved :: MIT License
Classifier: Programming Language :: Python
Classifier: Programming Language :: Python :: 3
Requires-Dist: tensorflow
Requires-Dist: sklearn
Requires-Dist: matplotlib
